esbot/__init__.py
esbot/core.py
esbot-50.9.dist-info/LICENSE
esbot-50.9.dist-info/METADATA
esbot-50.9.dist-info/WHEEL
esbot-50.9.dist-info/top_level.txt
esbot-50.9.dist-info/RECORD
