Metadata-Version: 2.2
Name: esbot
Version: 50.9
Summary: Easy Telegram Bot 
Home-page: https://t.me/xr_xr4
Author: Saoud
Author-email: ahmedsaoud0037@gmail.com
Classifier: Programming Language :: Python :: 3
Classifier: License :: OSI Approved :: MIT License
Classifier: Operating System :: OS Independent
Requires-Python: >=3.1
License-File: LICENSE
Requires-Dist: requests
Dynamic: author
Dynamic: author-email
Dynamic: classifier
Dynamic: home-page
Dynamic: requires-dist
Dynamic: requires-python
Dynamic: summary
